codecov_rs-0.1.0.dist-info/METADATA
codecov_rs-0.1.0.dist-info/WHEEL
codecov_rs-0.1.0.dist-info/licenses/LICENSE.md
codecov_rs/report.py
codecov_rs/report.pyi
codecov_rs/__init__.py
codecov_rs/py.typed
codecov_rs/_bindings.abi3.so
codecov_rs-0.1.0.dist-info/RECORD
