Metadata-Version: 2.3
Name: codecov_rs
Version: 0.1.0
Classifier: Programming Language :: Rust
Classifier: Programming Language :: Python :: Implementation :: CPython
Classifier: Programming Language :: Python :: Implementation :: PyPy
License-File: LICENSE.md
Author-email: Codecov <support@codecov.io>
Requires-Python: >=3.12
